llm_jsonl_converter/__init__.py
llm_jsonl_converter-2025.9.141156.dist-info/licenses/LICENSE
llm_jsonl_converter-2025.9.141156.dist-info/METADATA
llm_jsonl_converter-2025.9.141156.dist-info/WHEEL
llm_jsonl_converter-2025.9.141156.dist-info/top_level.txt
llm_jsonl_converter-2025.9.141156.dist-info/RECORD
