Metadata-Version: 2.4
Name: llm_jsonl_converter
Version: 2025.9.141156
Summary: A Python package for converting unstructured text into JSONL format using LLMs.
Home-page: https://github.com/chigwell/llm_jsonl_converter
Author: Eugene Evstafev
Author-email: hi@eugene.plus
License: MIT
Classifier: License :: OSI Approved :: MIT License
Classifier: Development Status :: 3 - Alpha
Classifier: Intended Audience :: Developers
Classifier: Programming Language :: Python :: 3
Classifier: Operating System :: OS Independent
Requires-Python: >=3.6
License-File: LICENSE
Requires-Dist: langchain-core
Requires-Dist: langchain-llm7
Requires-Dist: llmatch-messages==2025.9.131321
Requires-Dist: tqdm
Dynamic: author
Dynamic: author-email
Dynamic: classifier
Dynamic: description
Dynamic: description-content-type
Dynamic: home-page
Dynamic: license
Dynamic: license-file
Dynamic: requires-dist
Dynamic: requires-python
Dynamic: summary
